borco_pyside6_scintilla/__init__.py
borco_pyside6_scintilla-0.0.2.dist-info/METADATA
borco_pyside6_scintilla-0.0.2.dist-info/WHEEL
borco_pyside6_scintilla-0.0.2.dist-info/licenses/LICENSE.md
borco_pyside6_scintilla-0.0.2.dist-info/RECORD
